[
    { "detected_at": "03-27-25_10.01.00AM", "event_type": "Person", "location": "Barangay Hall" },
    { "detected_at": "03-27-25_10.01.00AM", "event_type": "Fire", "location": "Barangay Hall" },
    { "detected_at": "03-27-25_10.01.00AM", "event_type": "Fire", "location": "Barangay Hall" },
    { "detected_at": "03-27-25_10.01.00AM", "event_type": "Fire", "location": "Barangay Hall" },
    { "detected_at": "03-27-25_10.01.00AM", "event_type": "Fire", "location": "Barangay Hall" },
    { "detected_at": "03-27-25_10.01.00AM", "event_type": "Fire", "location": "Barangay Hall" },
    { "detected_at": "03-27-25_10.01.00AM", "event_type": "Fire", "location": "Barangay Hall" },
    { "detected_at": "03-02-25_10.01.00AM", "event_type": "Fire", "location": "Barangay Hall" },
    { "detected_at": "03-02-25_10.01.00AM", "event_type": "Flood", "location": "Santa Rita Church" },
    { "detected_at": "01-04-25_10.01.00AM", "event_type": "Fire", "location": "Purok 3" }
]
